PictSure/__init__.py
PictSure/model_PictSure.py
PictSure/model_embeddings.py
PictSure/normalization.py
PictSure/Embeddings/ViT.py
PictSure/Embeddings/__init__.py
pictsure-0.2.dist-info/licenses/LICENSE
pictsure-0.2.dist-info/METADATA
pictsure-0.2.dist-info/WHEEL
pictsure-0.2.dist-info/entry_points.txt
pictsure-0.2.dist-info/top_level.txt
pictsure-0.2.dist-info/RECORD
