Metadata-Version: 2.4
Name: PictSure
Version: 0.2
Summary: A package for generalized image classification using In-Context-Learning with PyTorch.
Author-email: Cornelius Wolff <cornelius.wolff@cwi.nl>, Lukas Schiesser <lukas.schiesser@dfki.de>
License: MIT License
Classifier: Programming Language :: Python :: 3
Classifier: License :: OSI Approved :: MIT License
Classifier: Operating System :: OS Independent
Requires-Python: >=3.9
License-File: LICENSE
Requires-Dist: torch>=2.7.0
Requires-Dist: torchvision>=0.22.0
Requires-Dist: numpy>=1.26.4
Requires-Dist: Pillow
Requires-Dist: click>=8.1.7
Requires-Dist: tqdm>=4.66.4
Requires-Dist: requests>=2.32.3
Requires-Dist: huggingface-hub>=0.33.1
Requires-Dist: safetensors>=0.5.3
Dynamic: license-file
